jellex/__init__.py
jellex/__main__.py
jellex/cli.py
jellex-0.5.7.dist-info/LICENSE
jellex-0.5.7.dist-info/METADATA
jellex-0.5.7.dist-info/WHEEL
jellex-0.5.7.dist-info/entry_points.txt
jellex-0.5.7.dist-info/top_level.txt
jellex-0.5.7.dist-info/RECORD
