Metadata-Version: 2.1
Name: jellex
Version: 0.5.7
Summary: TUI Jello Explorer - filter JSON and JSON Lines data with Python syntax.
Home-page: https://github.com/kellyjonbrazil/jellex
Author: Kelly Brazil
Author-email: kellyjonbrazil@gmail.com
License: MIT
Classifier: Programming Language :: Python :: 3
Classifier: License :: OSI Approved :: MIT License
Classifier: Operating System :: OS Independent
Classifier: Topic :: Utilities
Requires-Python: >=3.6
License-File: LICENSE
Requires-Dist: jello (>=1.4.4)
Requires-Dist: prompt-toolkit (==3.0.36)
Requires-Dist: Pygments (>=2.4.2)
